{
  "project": "knapsack_01_labA",
  "capacity": 50,
  "description": "Lab Inventory A - 15 items with varying value/weight ratios",
  "items": [
    {
      "id": "LAB-A-001",
      "value": 49,
      "weight": 13
    },
    {
      "id": "LAB-A-002",
      "value": 38,
      "weight": 15
    },
    {
      "id": "LAB-A-003",
      "value": 23,
      "weight": 9
    },
    {
      "id": "LAB-A-004",
      "value": 41,
      "weight": 7
    },
    {
      "id": "LAB-A-005",
      "value": 17,
      "weight": 13
    },
    {
      "id": "LAB-A-006",
      "value": 49,
      "weight": 11
    },
    {
      "id": "LAB-A-007",
      "value": 16,
      "weight": 17
    },
    {
      "id": "LAB-A-008",
      "value": 37,
      "weight": 4
    },
    {
      "id": "LAB-A-009",
      "value": 14,
      "weight": 14
    },
    {
      "id": "LAB-A-010",
      "value": 21,
      "weight": 2
    },
    {
      "id": "LAB-A-011",
      "value": 20,
      "weight": 5
    },
    {
      "id": "LAB-A-012",
      "value": 33,
      "weight": 6
    },
    {
      "id": "LAB-A-013",
      "value": 39,
      "weight": 11
    },
    {
      "id": "LAB-A-014",
      "value": 26,
      "weight": 3
    },
    {
      "id": "LAB-A-015",
      "value": 10,
      "weight": 2
    }
  ]
}